{
  "repositories": [
    {
      "slug": "happybudget-api",
      "description": "Backend API for Happy Budget Application & Framework",
      "createdAt": "2024-05-04T23:40:29.496Z",
      "updatedAt": "2024-05-04T23:40:29.496Z",
      "visible": true,
      "highlighted": true,
      "startDate": "2022-05-09T20:57:10.000Z",
      "npmPackageName": null,
      "skills": [
        "error-handling",
        "ci-cd",
        "postgresql",
        "aws-ec2",
        "django",
        "jwt-authentication",
        "aws",
        "application-security",
        "python",
        "django-rest-framework",
        "error-monitoring-alerting",
        "pytest",
        "unit-testing",
        "mock",
        "pyenv",
        "unittest",
        "pip",
        "tox",
        "logging-monitoring-infrastructure",
        "circleci",
        "poetry",
        "aws-elastic-beanstalk",
        "authentication-protocols",
        "security-practices",
        "aws-s3-storage",
        "pylint",
        "flake8",
        "sentry",
        "django-admin",
        "rest-api-design",
        "relational-databases"
      ]
    },
    {
      "slug": "nick.florin",
      "description": "Personal Website, Resume & Portfolio",
      "createdAt": "2024-05-04T23:40:29.496Z",
      "updatedAt": "2024-05-04T23:40:29.496Z",
      "visible": true,
      "highlighted": true,
      "startDate": "2024-01-09T17:01:19.000Z",
      "npmPackageName": null,
      "skills": [
        "error-handling",
        "ci-cd",
        "floating-ui",
        "responsive-design",
        "react",
        "postgresql",
        "html",
        "javascript",
        "css",
        "npm",
        "sass",
        "ui-ux",
        "nvm",
        "application-security",
        "prismajs",
        "pnpm",
        "typescript",
        "component-development",
        "error-monitoring-alerting",
        "tailwindcss",
        "unit-testing",
        "scss-css-modules",
        "logging-monitoring-infrastructure",
        "nextjs",
        "vercel",
        "ssr",
        "security-practices",
        "clerk",
        "jest",
        "rest-api-design",
        "relational-databases"
      ]
    },
    {
      "slug": "sportbook",
      "description": "Pick Up & Social Sports League Management",
      "createdAt": "2024-05-04T23:40:29.496Z",
      "updatedAt": "2024-05-04T23:40:29.496Z",
      "visible": true,
      "highlighted": true,
      "startDate": "2023-06-30T21:46:54.000Z",
      "npmPackageName": null,
      "skills": [
        "error-handling",
        "floating-ui",
        "responsive-design",
        "react",
        "postgresql",
        "html",
        "javascript",
        "css",
        "npm",
        "sass",
        "ui-ux",
        "nvm",
        "application-security",
        "prismajs",
        "pnpm",
        "typescript",
        "component-development",
        "tailwindcss",
        "unit-testing",
        "scss-css-modules",
        "logging-monitoring-infrastructure",
        "nextjs",
        "ssr",
        "security-practices",
        "clerk",
        "jest",
        "rest-api-design",
        "relational-databases"
      ]
    },
    {
      "slug": "git-blame-project",
      "description": "Tool for Performing Blame & Contribution Analysis per Line on Entire Project",
      "createdAt": "2024-05-04T23:40:29.496Z",
      "updatedAt": "2024-06-02T23:46:45.267Z",
      "visible": true,
      "highlighted": true,
      "startDate": "2022-07-09T15:38:13.000Z",
      "npmPackageName": null,
      "skills": ["pyenv", "pip"]
    },
    {
      "slug": "tooltrack",
      "description": "An application that allows users to monitor, manage and configure notifications and alerts that they will receive as it relates to inventory & price changes that occur for products offered by the woodworking hand tool manufacturer, Lie Nielsen.",
      "createdAt": "2024-06-02T22:55:04.739Z",
      "updatedAt": "2024-08-25T21:46:19.733Z",
      "visible": true,
      "highlighted": true,
      "startDate": "2024-05-11T22:31:03.000Z",
      "npmPackageName": null,
      "skills": [
        "error-handling",
        "ci-cd",
        "floating-ui",
        "data-scraping",
        "responsive-design",
        "react",
        "postgresql",
        "nodejs",
        "html",
        "javascript",
        "css",
        "npm",
        "sass",
        "ui-ux",
        "nvm",
        "application-security",
        "prismajs",
        "pnpm",
        "typescript",
        "component-development",
        "tailwindcss",
        "unit-testing",
        "logging-monitoring-infrastructure",
        "nextjs",
        "ssr",
        "security-practices",
        "clerk",
        "jest",
        "rest-api-design",
        "relational-databases"
      ]
    },
    {
      "slug": "pickyoptions",
      "description": "Options/Settings Framework for Python Packages",
      "createdAt": "2024-05-04T23:40:29.496Z",
      "updatedAt": "2024-09-21T16:28:18.881Z",
      "visible": true,
      "highlighted": false,
      "startDate": "2020-09-02T20:35:09.000Z",
      "npmPackageName": null,
      "skills": ["python", "pyenv", "pip", "flake8", "python-23-compatibility"]
    },
    {
      "slug": "casepilot-fe-test",
      "description": null,
      "createdAt": "2024-08-26T15:07:22.632Z",
      "updatedAt": "2024-08-26T15:07:22.632Z",
      "visible": false,
      "highlighted": false,
      "startDate": "2024-08-23T14:08:26.000Z",
      "npmPackageName": null,
      "skills": []
    },
    {
      "slug": "uslege-assign",
      "description": "USLege Assignment",
      "createdAt": "2024-06-02T22:55:04.739Z",
      "updatedAt": "2024-06-02T23:42:29.948Z",
      "visible": false,
      "highlighted": false,
      "startDate": "2024-05-29T14:23:56.000Z",
      "npmPackageName": null,
      "skills": []
    },
    {
      "slug": "hippo-scribe-interview",
      "description": "Hippo Scribe Interview",
      "createdAt": "2024-06-02T22:55:04.739Z",
      "updatedAt": "2024-06-02T23:42:33.334Z",
      "visible": false,
      "highlighted": false,
      "startDate": "2024-05-20T16:07:48.000Z",
      "npmPackageName": null,
      "skills": []
    },
    {
      "slug": "termx",
      "description": "Advanced Terminal Utilities",
      "createdAt": "2024-05-04T23:40:29.496Z",
      "updatedAt": "2024-06-02T23:46:11.102Z",
      "visible": false,
      "highlighted": false,
      "startDate": "2019-06-13T03:38:11.000Z",
      "npmPackageName": null,
      "skills": []
    },
    {
      "slug": "util",
      "description": "A collection of random TS utilities that I have used in the past.",
      "createdAt": "2024-05-04T23:40:29.496Z",
      "updatedAt": "2024-06-02T23:46:12.544Z",
      "visible": false,
      "highlighted": false,
      "startDate": "2024-01-13T20:30:29.000Z",
      "npmPackageName": null,
      "skills": []
    },
    {
      "slug": "nextjs-starter-template",
      "description": "A bells & whistles starter template for NextJS projects",
      "createdAt": "2024-05-04T23:40:29.496Z",
      "updatedAt": "2024-06-02T23:46:24.421Z",
      "visible": false,
      "highlighted": false,
      "startDate": "2023-04-23T14:36:20.000Z",
      "npmPackageName": null,
      "skills": []
    },
    {
      "slug": "diff",
      "description": "Diff Engine for Analysis Between 2 Datasets",
      "createdAt": "2024-08-26T15:07:22.632Z",
      "updatedAt": "2024-08-26T15:07:22.632Z",
      "visible": false,
      "highlighted": false,
      "startDate": "2020-09-02T19:54:59.000Z",
      "npmPackageName": null,
      "skills": []
    },
    {
      "slug": "portfolio-frontend",
      "description": "React Application for Personal Portfolio (Old)",
      "createdAt": "2024-05-04T23:40:29.496Z",
      "updatedAt": "2024-06-02T23:46:28.840Z",
      "visible": true,
      "highlighted": false,
      "startDate": "2024-04-16T23:24:19.097Z",
      "npmPackageName": null,
      "skills": ["react", "javascript", "css", "npm", "security-practices"]
    },
    {
      "slug": "coinscore",
      "description": "Coin Score Landing Repository",
      "createdAt": "2024-05-04T23:40:29.496Z",
      "updatedAt": "2024-06-02T23:46:32.726Z",
      "visible": false,
      "highlighted": false,
      "startDate": "2017-10-13T03:50:05.000Z",
      "npmPackageName": null,
      "skills": []
    },
    {
      "slug": "pickysettings",
      "description": "Configurable settings for your Python packages and projects.",
      "createdAt": "2024-05-04T23:40:29.496Z",
      "updatedAt": "2024-06-02T23:46:38.753Z",
      "visible": false,
      "highlighted": false,
      "startDate": "2019-07-07T02:55:05.000Z",
      "npmPackageName": null,
      "skills": []
    },
    {
      "slug": "portfolio-drf",
      "description": "Personal Portfolio API w Django REST Framework (Old)",
      "createdAt": "2024-05-04T23:40:29.496Z",
      "updatedAt": "2024-09-21T16:28:50.902Z",
      "visible": true,
      "highlighted": false,
      "startDate": "2020-03-14T03:26:28.000Z",
      "npmPackageName": null,
      "skills": [
        "django",
        "python",
        "django-rest-framework",
        "pyenv",
        "pip",
        "flake8",
        "rest-api-design",
        "relational-databases"
      ]
    },
    {
      "slug": "happybudget",
      "description": "HappyBudget Cloud Based Budgeting (Original Work)",
      "createdAt": "2024-08-26T15:07:22.632Z",
      "updatedAt": "2024-08-26T15:08:06.188Z",
      "visible": true,
      "highlighted": true,
      "startDate": "2022-05-11T15:25:55.000Z",
      "npmPackageName": null,
      "skills": [
        "error-handling",
        "css",
        "npm",
        "ui-ux",
        "application-security",
        "component-development",
        "error-monitoring-alerting",
        "logging-monitoring-infrastructure",
        "security-practices"
      ]
    },
    {
      "slug": "enumerated-literals",
      "description": "A utility for managing enumerated, string literal constants in TypeScript",
      "createdAt": "2024-06-04T16:52:27.922Z",
      "updatedAt": "2024-09-02T20:19:57.658Z",
      "visible": true,
      "highlighted": true,
      "startDate": "2024-05-31T18:03:51.000Z",
      "npmPackageName": "enumerated-literals",
      "skills": [
        "ci-cd",
        "npm",
        "nvm",
        "typescript",
        "unit-testing",
        "codecov",
        "package-dependency-management",
        "jest"
      ]
    },
    {
      "slug": "instagram-attack",
      "description": "CLI Application Based on Python3's Asyncio for Systematically Guessing Instagram Passwords",
      "createdAt": "2024-05-04T23:40:29.496Z",
      "updatedAt": "2024-09-17T00:54:40.036Z",
      "visible": true,
      "highlighted": false,
      "startDate": "2019-03-25T00:52:55.000Z",
      "npmPackageName": null,
      "skills": ["asyncio", "python"]
    },
    {
      "slug": "django-polymorphic-bulk-create",
      "description": "Experimental Code for Bulk Create Behavior with Polymorphic Models",
      "createdAt": "2024-05-04T23:40:29.496Z",
      "updatedAt": "2024-09-17T00:55:11.313Z",
      "visible": true,
      "highlighted": true,
      "startDate": "2021-07-03T16:37:16.000Z",
      "npmPackageName": null,
      "skills": ["django", "python", "django-rest-framework"]
    },
    {
      "slug": "pebl",
      "description": "iOS Dating Application Based on Event/Date Based Matching",
      "createdAt": "2024-05-04T23:40:29.496Z",
      "updatedAt": "2024-09-17T00:55:28.944Z",
      "visible": true,
      "highlighted": true,
      "startDate": "2017-12-09T01:46:23.000Z",
      "npmPackageName": null,
      "skills": ["ui-ux", "logging-monitoring-infrastructure", "swift", "security-practices"]
    }
  ]
}
